[
    {
        "title": "A Random Walk Down Wall Street: The Time-Tested Strategy for Successful Investing (Completely Revised and Updated)",
        "genre": "Business & Economics",
        "ISBN": "9780393081695"
    },
    {
        "title": "Absolut Book",
        "genre": "Business & Economics",
        "ISBN": "9781885203328"
    },
    {
        "title": "Aerotropolis",
        "genre": "Business & Economics",
        "ISBN": "9780374100193"
    },
    {
        "title": "Boomerang: Travels in the New Third World",
        "genre": "Business & Economics",
        "ISBN": "9780393081817"
    },
    {
        "title": "Competing on Thought Leadership",
        "genre": "Business & Economics",
        "ISBN": "9781646871001"
    },
    {
        "title": "Creating a World Without Poverty",
        "genre": "Business & Economics",
        "ISBN": "9781586486679"
    },
    {
        "title": "Eat the Rich",
        "genre": "Business & Economics",
        "ISBN": "9780871137609"
    },
    {
        "title": "Financial Feminist",
        "genre": "Business & Economics",
        "ISBN": "9780063260269"
    },
    {
        "title": "Flash Boys: A Wall Street Revolt",
        "genre": "Business & Economics",
        "ISBN": "9780393244663"
    },
    {
        "title": "Guiding Lights",
        "genre": "Business & Economics",
        "ISBN": "9780375761027"
    },
    {
        "title": "Incorporating Your Business For Dummies",
        "category": "Business & Economics",
        "isbn": "9780764553417"
    },
    {
        "title": "Life Is Good",
        "category": "Business & Economics",
        "isbn": "9781426215636"
    },
    {
        "title": "Live It, Love It, Earn it",
        "category": "Business & Economics",
        "isbn": "9781591842552"
    },
    {
        "title": "Nudge",
        "category": "Business & Economics",
        "isbn": "9780143115267"
    },
    {
        "title": "Owning Up",
        "category": "Business & Economics",
        "isbn": "9780470397671"
    },
    {
        "title": "Silos, Politics and Turf Wars",
        "category": "Business & Economics",
        "isbn": "9780787976385"
    },
    {
        "title": "Start with Why",
        "category": "Business & Economics",
        "isbn": "9781591846444"
    },
    {
        "title": "Successful Small Business Management",
        "category": "Management",
        "isbn": "9780814453940"
    },
    {
        "title": "Survival of the Savvy",
        "category": "Business & Economics",
        "isbn": "9780743262545"
    },
    {
        "title": "SPIN Selling",
        "category": "Business & Economics",
        "isbn": "9780070511132"
    },
    {
        "title": "The Barefoot Investor",
        "category": "Business & Economics",
        "isbn": "9780730324218"
    },
    {
        "title": "The Changemaker",
        "category": "Business & Economics",
        "isbn": "9781946633736"
    },
    {
        "title": "The Corporate Lattice",
        "category": "Business & Economics",
        "isbn": "9781422155165"
    },
    {
        "title": "The Great Crash 1929",
        "category": "Business & Economics",
        "isbn": "9780547248165"
    },
    {
        "title": "The Leadership Challenge",
        "category": "Business & Economics",
        "isbn": "9781119278962"
    },
    {
        "title": "The Rational Optimist",
        "category": "Business & Economics",
        "isbn": "9780061452062"
    },
    {
        "title": "The Richest Man in Babylon",
        "category": "Business & Economics",
        "isbn": "9780451205360"
    },
    {
        "title": "Unstoppable",
        "category": "Business & Economics",
        "isbn": "9781422103661"
    },
    {
        "title": "Vendetta",
        "category": "American Express Company",
        "isbn": "9780060167592"
    },
    {
        "title": "Why I Left Goldman Sachs",
        "category": "Investment banking",
        "isbn": "9781455558902"
    },
    {
        "title": "Working Backwards",
        "category": "Business & Economics",
        "isbn": "9781250267597"
    }
]